odoo/addons/l10n_ro_account_bank_statement_report/README.rst
odoo/addons/l10n_ro_account_bank_statement_report/__init__.py
odoo/addons/l10n_ro_account_bank_statement_report/__manifest__.py
odoo/addons/l10n_ro_account_bank_statement_report/i18n/l10n_ro_account_bank_statement_report.pot
odoo/addons/l10n_ro_account_bank_statement_report/i18n/ro.po
odoo/addons/l10n_ro_account_bank_statement_report/models/__init__.py
odoo/addons/l10n_ro_account_bank_statement_report/models/account_bank_statement.py
odoo/addons/l10n_ro_account_bank_statement_report/readme/CONTRIBUTORS.rst
odoo/addons/l10n_ro_account_bank_statement_report/readme/DESCRIPTION.rst
odoo/addons/l10n_ro_account_bank_statement_report/readme/INSTALL.rst
odoo/addons/l10n_ro_account_bank_statement_report/readme/USAGE.rst
odoo/addons/l10n_ro_account_bank_statement_report/static/description/icon.png
odoo/addons/l10n_ro_account_bank_statement_report/static/description/icon.svg
odoo/addons/l10n_ro_account_bank_statement_report/static/description/index.html
odoo/addons/l10n_ro_account_bank_statement_report/views/report_l10n_ro_statement_daily.xml
odoo/addons/l10n_ro_account_bank_statement_report/views/report_l10n_ro_statement_period.xml
odoo/addons/l10n_ro_account_bank_statement_report/views/report_statement.xml
odoo14_addon_l10n_ro_account_bank_statement_report-14.0.1.6.0.dist-info/METADATA
odoo14_addon_l10n_ro_account_bank_statement_report-14.0.1.6.0.dist-info/WHEEL
odoo14_addon_l10n_ro_account_bank_statement_report-14.0.1.6.0.dist-info/top_level.txt
odoo14_addon_l10n_ro_account_bank_statement_report-14.0.1.6.0.dist-info/RECORD
